Workbook

Sheet Read Me
A1: Pitara — cost & profit model
A2: Play with the numbers: change the BLUE cells on the Inputs sheet and every other sheet recalculates.
A4: HOW TO USE
A5: 1. Inputs: edit blue cells. Yellow-filled blue cells are the main levers (users, GB per user, prices, annual share).
A6: 2. Model: monthly costs and profit for the three scenarios, using the storage backend chosen on Inputs (GCS / R2 / B2).
A7: 3. Backends: the same three scenarios priced on each storage provider side by side, whatever Inputs says.
A8: 4. Price Grid: profit at different monthly prices (edit the blue prices in column A).
A10: COLOUR CODE
A11: Blue text = typed-in input · Black = formula · Green = pulled from another sheet · Yellow fill = key lever.
A13: TWO PROFIT LINES — read both
A14: 'You do the work': you do maintenance and support yourself, so only cash costs count (infrastructure, card fees, tooling, accounting/legal).
A15: 'You pay for them': also counts contractor maintenance and paid support at market rates. This is the honest long-run view.
... A27: Caveat: cost per user falls with scale only because fixed items are assumed to grow slowly — test your own numbers.

Sheet Inputs
A1: Inputs — change the blue cells (yellow = main levers)
A2: Scenarios are columns B–D; everything else is a single value in column B.
A4: Scenario | B4: Small | C4: Medium | D4: Large | E4: Notes / source
A5: Paying cloud users | B5: 100 | C5: 500 | D5: 1000 | E5: Your scenarios (100 / 500 / 1,000).
A6: Average GB stored per user | B6: 20 | C6: 20 | D6: 20 | E6: Your assumption (20 GB). A scans-and-PDFs vault is usually far smaller — try 3–5 GB.
A7: Downloads per user per month (GB) | B7: 1 | C7: 1 | D7: 1 | E7: Assumption: ~5% of stored data opened per month. Design rule: download on demand, never the whole vault.
A8: Other infrastructure $/month | B8: 4 | C8: 10 | D8: 30 | E8: Assumption: Firestore, Cloud Functions, Hosting, Auth at these volumes.
A9: Tooling $/month | B9: 30 | C9: 60 | D9: 100 | E9: Assumption: transactional email, error monitoring, helpdesk, domain.
A10: Accounting, legal upkeep, insurance $/month | B10: 150 | C10: 200 | D10: 300 | E10: Rough assumption — get real quotes.
A11: Maintenance hours per month | B11: 10 | C11: 20 | D11: 30 | E11: Assumption: OS/dependency upkeep, bug fixes (this project has needed a lot).
A13: Rates
A14: Maintenance rate $/hour | B14: 50 | E14: Assumption: contractor rate.
A15: Share of users contacting support per month | B15: 0.1 | E15: Assumption.
A16: Minutes per support ticket | B16: 20 | E16: Assumption.
A17: Support rate $/hour | B17: 25 | E17: Assumption: part-time support.
A19: Pricing
A20: Monthly plan price ($) | B20: 4.99 | E20: Recommended starting point. Previous doc said $3.99.
A21: Annual plan price ($) | B21: 49.99 | E21: Recommended starting point. Previous doc said $39.99.
A22: Share of paying users on the annual plan | B22: 0.7 | E22: Assumption. Annual billing cuts card fees from ~8–10% to under 4% of the charge.
A23: VAT / GST included in advertised price | B23: 0 | E23: Default 0%. If your prices include e.g. 20% VAT, enter 20% — revenue is then shown net of it.
A25: Card payment fees (Stripe, UK account)
A26: Card fee % (blended) | B26: 0.025 | E26: UK cards 1.5%, EEA 2.5%, international 3.25% (+20p each). 2.5% is a blended guess for a UK/India mix.
A27: Stripe Billing % | B27: 0.007 | E27: Sources disagree: 0.7% vs 0.25%. Higher figure used.
A28: Fixed fee per charge ($) | B28: 0.26 | E28: 20p converted to dollars.
A30: Storage backend
A31: Storage backend used on the Model sheet | B31: GCS | E31: Pick GCS (Firebase / Google Cloud Storage), R2 (Cloudflare) or B2 (Backblaze). Drop-down.
A32: Google Cloud Storage $/GB-month | B32: 0.023 | E32: EU region standard storage (US regions ~$0.020).
A33: GCS downloads $/GB — first tier | B33: 0.12 | E33: Internet egress, first 1,000 GB / month.
A34: GCS downloads $/GB — second tier | B34: 0.11 | E34: Next 9,000 GB / month.
A35: GCS downloads $/GB — third tier | B35: 0.08 | E35: Beyond 10,000 GB / month.
A36: GCS first tier size (GB) | B36: 1000
A37: GCS second tier size (GB) | B37: 9000
A38: Cloudflare R2 storage $/GB-month | B38: 0.015 | E38: Downloads are free.
A39: R2 free storage (GB) | B39: 10 | E39: Monthly free allowance.
A40: Backblaze B2 storage $/GB-month | B40: 0.00695 | E40: $6.95 per TB.
A41: B2 free downloads, multiple of stored data | B41: 3 | E41: Free up to 3x average stored data.
A42: B2 download overage $/GB | B42: 0.01 | E42: Beyond the free multiple.

Sheet Model
A1: Model — monthly figures (USD)
A2: ="Storage backend: "&Inputs!B31 -> Storage backend: GCS
A4: Metric | B4: =Inputs!B4 -> Small | C4: =Inputs!C4 -> Medium | D4: =Inputs!D4 -> Large | E4: How it's calculated
A5: Volume
A6: Paying cloud users | B6: =Inputs!B5 -> 100 | C6: =Inputs!C5 -> 500 | D6: =Inputs!D5 -> 1000
A7: Total stored (GB) | B7: =Inputs!B5*Inputs!B6 -> 2000 | C7: =Inputs!C5*Inputs!C6 -> 10000 | D7: =Inputs!D5*Inputs!D6 -> 20000 | E7: users × GB per user
A8: Total downloads per month (GB) | B8: =Inputs!B5*Inputs!B7 -> 100 | C8: =Inputs!C5*Inputs!C7 -> 500 | D8: =Inputs!D5*Inputs!D7 -> 1000 | E8: users × download GB per user
A9: Infrastructure
A10: Storage | B10: =IF(Inputs!$B$31="GCS",B7*Inputs!$B$32,IF(Inputs!$B$31="R2",MAX(B7-Inputs!$B$39,0)*Inputs!$B$38,B7*Inputs!$B$40)) -> 46 | C10: =IF(Inputs!$B$31="GCS",C7*Inputs!$B$32,IF(Inputs!$B$31="R2",MAX(C7-Inputs!$B$39,0)*Inputs!$B$38,C7*Inputs!$B$40)) -> 230 | D10: =IF(Inputs!$B$31="GCS",D7*Inputs!$B$32,IF(Inputs!$B$31="R2",MAX(D7-Inputs!$B$39,0)*Inputs!$B$38,D7*Inputs!$B$40)) -> 460 | E10: Per-GB price of the chosen backend × stored GB
A11: Downloads (egress) | B11: =IF(Inputs!$B$31="GCS",MIN(B8,Inputs!$B$36)*Inputs!$B$33+MIN(MAX(B8-Inputs!$B$36,0),Inputs!$B$37)*Inputs!$B$34+MAX(B8-Inputs!$B$36-Inputs!$B$37,0)*Inputs!$B$35,IF(Inputs!$B$31="B2",MAX(B8-Inputs!$B$41*B7,0)*Inputs!$B$42,0)) -> 12 | C11: =IF(Inputs!$B$31="GCS",MIN(C8,Inputs!$B$36)*Inputs!$B$33+MIN(MAX(C8-Inputs!$B$36,0),Inputs!$B$37)*Inputs!$B$34+MAX(C8-Inputs!$B$36-Inputs!$B$37,0)*Inputs!$B$35,IF(Inputs!$B$31="B2",MAX(C8-Inputs!$B$41*C7,0)*Inputs!$B$42,0)) -> 60 | D11: =IF(Inputs!$B$31="GCS",MIN(D8,Inputs!$B$36)*Inputs!$B$33+MIN(MAX(D8-Inputs!$B$36,0),Inputs!$B$37)*Inputs!$B$34+MAX(D8-Inputs!$B$36-Inputs!$B$37,0)*Inputs!$B$35,IF(Inputs!$B$31="B2",MAX(D8-Inputs!$B$41*D7,0)*Inputs!$B$42,0)) -> 120 | E11: GCS: tiered; R2: free; B2: free up to 3x stored
A12: Other infrastructure (Firestore, Functions, Hosting) | B12: =Inputs!B8 -> 4 | C12: =Inputs!C8 -> 10 | D12: =Inputs!D8 -> 30
A13: Infrastructure total | B13: =SUM(B10:B12) -> 62 | C13: =SUM(C10:C12) -> 300 | D13: =SUM(D10:D12) -> 610
A14: Infrastructure per user per month | B14: =IFERROR(B13/B6,0) -> 0.62 | C14: =IFERROR(C13/C6,0) -> 0.6 | D14: =IFERROR(D13/D6,0) -> 0.61
A15: Revenue and card fees
A16: Gross revenue per user per month (blended) | B16: =Inputs!$B$22*Inputs!$B$21/12+(1-Inputs!$B$22)*Inputs!$B$20 -> 4.4130833 | C16: =Inputs!$B$22*Inputs!$B$21/12+(1-Inputs!$B$22)*Inputs!$B$20 -> 4.4130833 | D16: =Inputs!$B$22*Inputs!$B$21/12+(1-Inputs!$B$22)*Inputs!$B$20 -> 4.4130833 | E16: annual share × annual/12 + monthly share × monthly price
A17: Card fee per user per month (blended) | B17: =Inputs!$B$22*((Inputs!$B$21*(Inputs!$B$26+Inputs!$B$27)+Inputs!$B$28)/12)+(1-Inputs!$B$22)*(Inputs!$B$20*(Inputs!$B$26+Inputs!$B$27)+Inputs!$B$28) -> 0.23438533 | C17: =Inputs!$B$22*((Inputs!$B$21*(Inputs!$B$26+Inputs!$B$27)+Inputs!$B$28)/12)+(1-Inputs!$B$22)*(Inputs!$B$20*(Inputs!$B$26+Inputs!$B$27)+Inputs!$B$28) -> 0.23438533 | D17: =Inputs!$B$22*((Inputs!$B$21*(Inputs!$B$26+Inputs!$B$27)+Inputs!$B$28)/12)+(1-Inputs!$B$22)*(Inputs!$B$20*(Inputs!$B$26+Inputs!$B$27)+Inputs!$B$28) -> 0.23438533 | E17: (price × (card % + Billing %) + fixed fee), per charge, spread over the billing period
A18: Gross revenue (what customers pay) | B18: =B6*B16 -> 441.30833 | C18: =C6*C16 -> 2206.5417 | D18: =D6*D16 -> 4413.0833
A19: Less: VAT / GST portion | B19: =B18-B18/(1+Inputs!$B$23) -> 0 | C19: =C18-C18/(1+Inputs!$B$23) -> 0 | D19: =D18-D18/(1+Inputs!$B$23) -> 0 | E19: Zero unless you enter a tax rate on Inputs
A20: Net revenue | B20: =B18-B19 -> 441.30833 | C20: =C18-C19 -> 2206.5417 | D20: =D18-D19 -> 4413.0833
A21: Card fees | B21: =B6*B17 -> 23.438533 | C21: =C6*C17 -> 117.19267 | D21: =D6*D17 -> 234.38533
A22: Other cash costs
A23: Tooling (email, monitoring, helpdesk, domain) | B23: =Inputs!B9 -> 30 | C23: =Inputs!C9 -> 60 | D23: =Inputs!D9 -> 100
A24: Accounting, legal upkeep, insurance | B24: =Inputs!B10 -> 150 | C24: =Inputs!C10 -> 200 | D24: =Inputs!D10 -> 300
A25: Cash cost — no salary for you | B25: =B13+B21+B23+B24 -> 265.43853 | C25: =C13+C21+C23+C24 -> 677.19267 | D25: =D13+D21+D23+D24 -> 1244.3853 | E25: infrastructure + card fees + tooling + accounting/legal
A26: People
A27: Maintenance (contractor) | B27: =Inputs!B11*Inputs!$B$14 -> 500 | C27: =Inputs!C11*Inputs!$B$14 -> 1000 | D27: =Inputs!D11*Inputs!$B$14 -> 1500 | E27: hours × hourly rate
A28: Customer support | B28: =B6*Inputs!$B$15*Inputs!$B$16/60*Inputs!$B$17 -> 83.333333 | C28: =C6*Inputs!$B$15*Inputs!$B$16/60*Inputs!$B$17 -> 416.66667 | D28: =D6*Inputs!$B$15*Inputs!$B$16/60*Inputs!$B$17 -> 833.33333 | E28: users × share contacting × minutes ÷ 60 × rate
A29: Full cost | B29: =B25+B27+B28 -> 848.77187 | C29: =C25+C27+C28 -> 2093.8593 | D29: =D25+D27+D28 -> 3577.7187
A30: Result
A31: PROFIT if you do maintenance & support yourself | B31: =B20-B25 -> 175.8698 | C31: =C20-C25 -> 1529.349 | D31: =D20-D25 -> 3168.698
A32: PROFIT if you pay for them | B32: =B20-B29 -> -407.46353 | C32: =C20-C29 -> 112.68233 | D32: =D20-D29 -> 835.36467
A33: Full cost per user per month | B33: =IFERROR(B29/B6,0) -> 8.4877187 | C33: =IFERROR(C29/C6,0) -> 4.1877187 | D33: =IFERROR(D29/D6,0) -> 3.5777187
A34: Net revenue per user per month | B34: =IFERROR(B20/B6,0) -> 4.4130833 | C34: =IFERROR(C20/C6,0) -> 4.4130833 | D34: =IFERROR(D20/D6,0) -> 4.4130833
A35: Margin (paying for staff) | B35: =IFERROR(B32/B20,0) -> -0.92330804 | C35: =IFERROR(C32/C20,0) -> 0.051067394 | D35: =IFERROR(D32/D20,0) -> 0.18929275
A36: Break-even monthly price (annual price keeps the same ratio to monthly)
A37: Helper: gross revenue per $1 of monthly price | B37: =Inputs!$B$22*(Inputs!$B$21/Inputs!$B$20)/12+(1-Inputs!$B$22) -> 0.88438544 | C37: =Inputs!$B$22*(Inputs!$B$21/Inputs!$B$20)/12+(1-Inputs!$B$22) -> 0.88438544 | D37: =Inputs!$B$22*(Inputs!$B$21/Inputs!$B$20)/12+(1-Inputs!$B$22) -> 0.88438544 | E37: blended plan mix
A38: Helper: fixed card fee per user per month | B38: =Inputs!$B$28*(Inputs!$B$22/12+(1-Inputs!$B$22)) -> 0.093166667 | C38: =Inputs!$B$28*(Inputs!$B$22/12+(1-Inputs!$B$22)) -> 0.093166667 | D38: =Inputs!$B$28*(Inputs!$B$22/12+(1-Inputs!$B$22)) -> 0.093166667
A39: Break-even monthly price — you do the work | B39: =IFERROR(((B13+B23+B24)/B6+B38)/(B37*(1/(1+Inputs!$B$23)-(Inputs!$B$26+Inputs!$B$27))),0) -> 2.9356505 | C39: =IFERROR(((C13+C23+C24)/C6+C38)/(C37*(1/(1+Inputs!$B$23)-(Inputs!$B$26+Inputs!$B$27))),0) -> 1.4171099 | D39: =IFERROR(((D13+D23+D24)/D6+D38)/(D37*(1/(1+Inputs!$B$23)-(Inputs!$B$26+Inputs!$B$27))),0) -> 1.288618 | E39: lowest monthly price at which profit = 0
A40: Break-even monthly price — paying staff | B40: =IFERROR(((B29-B21)/B6+B38)/(B37*(1/(1+Inputs!$B$23)-(Inputs!$B$26+Inputs!$B$27))),0) -> 9.7496148 | C40: =IFERROR(((C29-C21)/C6+C38)/(C37*(1/(1+Inputs!$B$23)-(Inputs!$B$26+Inputs!$B$27))),0) -> 4.7267497 | D40: =IFERROR(((D29-D21)/D6+D38)/(D37*(1/(1+Inputs!$B$23)-(Inputs!$B$26+Inputs!$B$27))),0) -> 4.0142037 | E40: compare with the price you actually charge

Sheet Backends
A1: Backends — same scenarios on each storage provider (USD per month)
A2: Ignores the backend picked on Inputs. Everything else comes from the Model sheet.
A4: Metric | B4: =Inputs!B4 -> Small | C4: =Inputs!C4 -> Medium | D4: =Inputs!D4 -> Large
A5: Google Cloud Storage (Firebase)
A6: Storage | B6: =Model!B7*Inputs!$B$32 -> 46 | C6: =Model!C7*Inputs!$B$32 -> 230 | D6: =Model!D7*Inputs!$B$32 -> 460
A7: Downloads | B7: =MIN(Model!B8,Inputs!$B$36)*Inputs!$B$33+MIN(MAX(Model!B8-Inputs!$B$36,0),Inputs!$B$37)*Inputs!$B$34+MAX(Model!B8-Inputs!$B$36-Inputs!$B$37,0)*Inputs!$B$35 -> 12 | C7: =MIN(Model!C8,Inputs!$B$36)*Inputs!$B$33+MIN(MAX(Model!C8-Inputs!$B$36,0),Inputs!$B$37)*Inputs!$B$34+MAX(Model!C8-Inputs!$B$36-Inputs!$B$37,0)*Inputs!$B$35 -> 60 | D7: =MIN(Model!D8,Inputs!$B$36)*Inputs!$B$33+MIN(MAX(Model!D8-Inputs!$B$36,0),Inputs!$B$37)*Inputs!$B$34+MAX(Model!D8-Inputs!$B$36-Inputs!$B$37,0)*Inputs!$B$35 -> 120
A8: Other infrastructure | B8: =Model!B12 -> 4 | C8: =Model!C12 -> 10 | D8: =Model!D12 -> 30
A9: Infrastructure total | B9: =SUM(B6:B8) -> 62 | C9: =SUM(C6:C8) -> 300 | D9: =SUM(D6:D8) -> 610
A10: Infrastructure per user per month | B10: =IFERROR(B9/Model!B6,0) -> 0.62 | C10: =IFERROR(C9/Model!C6,0) -> 0.6 | D10: =IFERROR(D9/Model!D6,0) -> 0.61
A11: Profit — you do the work | B11: =Model!B20-(B9+Model!B21+Model!B23+Model!B24) -> 175.8698 | C11: =Model!C20-(C9+Model!C21+Model!C23+Model!C24) -> 1529.349 | D11: =Model!D20-(D9+Model!D21+Model!D23+Model!D24) -> 3168.698
A12: Profit — you pay for maintenance & support | B12: =Model!B20-(B9+Model!B21+Model!B23+Model!B24+Model!B27+Model!B28) -> -407.46353 | C12: =Model!C20-(C9+Model!C21+Model!C23+Model!C24+Model!C27+Model!C28) -> 112.68233 | D12: =Model!D20-(D9+Model!D21+Model!D23+Model!D24+Model!D27+Model!D28) -> 835.36467
A14: Cloudflare R2
A15: Storage | B15: =MAX(Model!B7-Inputs!$B$39,0)*Inputs!$B$38 -> 29.85 | C15: =MAX(Model!C7-Inputs!$B$39,0)*Inputs!$B$38 -> 149.85 | D15: =MAX(Model!D7-Inputs!$B$39,0)*Inputs!$B$38 -> 299.85
A16: Downloads | B16: =0 -> 0 | C16: =0 -> 0 | D16: =0 -> 0
A17: Other infrastructure | B17: =Model!B12 -> 4 | C17: =Model!C12 -> 10 | D17: =Model!D12 -> 30
A18: Infrastructure total | B18: =SUM(B15:B17) -> 33.85 | C18: =SUM(C15:C17) -> 159.85 | D18: =SUM(D15:D17) -> 329.85
A19: Infrastructure per user per month | B19: =IFERROR(B18/Model!B6,0) -> 0.3385 | C19: =IFERROR(C18/Model!C6,0) -> 0.3197 | D19: =IFERROR(D18/Model!D6,0) -> 0.32985
A20: Profit — you do the work | B20: =Model!B20-(B18+Model!B21+Model!B23+Model!B24) -> 204.0198 | C20: =Model!C20-(C18+Model!C21+Model!C23+Model!C24) -> 1669.499 | D20: =Model!D20-(D18+Model!D21+Model!D23+Model!D24) -> 3448.848
A21: Profit — you pay for maintenance & support | B21: =Model!B20-(B18+Model!B21+Model!B23+Model!B24+Model!B27+Model!B28) -> -379.31353 | C21: =Model!C20-(C18+Model!C21+Model!C23+Model!C24+Model!C27+Model!C28) -> 252.83233 | D21: =Model!D20-(D18+Model!D21+Model!D23+Model!D24+Model!D27+Model!D28) -> 1115.5147
A23: Backblaze B2
A24: Storage | B24: =Model!B7*Inputs!$B$40 -> 13.9 | C24: =Model!C7*Inputs!$B$40 -> 69.5 | D24: =Model!D7*Inputs!$B$40 -> 139
A25: Downloads | B25: =MAX(Model!B8-Inputs!$B$41*Model!B7,0)*Inputs!$B$42 -> 0 | C25: =MAX(Model!C8-Inputs!$B$41*Model!C7,0)*Inputs!$B$42 -> 0 | D25: =MAX(Model!D8-Inputs!$B$41*Model!D7,0)*Inputs!$B$42 -> 0
A26: Other infrastructure | B26: =Model!B12 -> 4 | C26: =Model!C12 -> 10 | D26: =Model!D12 -> 30
A27: Infrastructure total | B27: =SUM(B24:B26) -> 17.9 | C27: =SUM(C24:C26) -> 79.5 | D27: =SUM(D24:D26) -> 169
A28: Infrastructure per user per month | B28: =IFERROR(B27/Model!B6,0) -> 0.179 | C28: =IFERROR(C27/Model!C6,0) -> 0.159 | D28: =IFERROR(D27/Model!D6,0) -> 0.169
A29: Profit — you do the work | B29: =Model!B20-(B27+Model!B21+Model!B23+Model!B24) -> 219.9698 | C29: =Model!C20-(C27+Model!C21+Model!C23+Model!C24) -> 1749.849 | D29: =Model!D20-(D27+Model!D21+Model!D23+Model!D24) -> 3609.698
A30: Profit — you pay for maintenance & support | B30: =Model!B20-(B27+Model!B21+Model!B23+Model!B24+Model!B27+Model!B28) -> -363.36353 | C30: =Model!C20-(C27+Model!C21+Model!C23+Model!C24+Model!C27+Model!C28) -> 333.18233 | D30: =Model!D20-(D27+Model!D21+Model!D23+Model!D24+Model!D27+Model!D28) -> 1276.3647

Sheet Price Grid
A1: Price Grid — monthly profit at different prices (USD)
A2: Edit the blue monthly prices in column A. Annual price = monthly × the ratio of your annual/monthly prices on Inputs. Uses the storage backend chosen on Inputs.
C4: You do maintenance & support | F4: You pay for maintenance & support
A5: Monthly price | B5: Annual price | C5: =Inputs!B4&" ("&TEXT(Inputs!B5,"#,##0")&")" -> Small (100) | D5: =Inputs!C4&" ("&TEXT(Inputs!C5,"#,##0")&")" -> Medium (500) | E5: =Inputs!D4&" ("&TEXT(Inputs!D5,"#,##0")&")" -> Large (1,000) | F5: =Inputs!B4&" ("&TEXT(Inputs!B5,"#,##0")&")" -> Small (100) | G5: =Inputs!C4&" ("&TEXT(Inputs!C5,"#,##0")&")" -> Medium (500) | H5: =Inputs!D4&" ("&TEXT(Inputs!D5,"#,##0")&")" -> Large (1,000)
A6: 2.99 | B6: =A6*Inputs!$B$21/Inputs!$B$20 -> 29.953928 | C6: =Model!$B$6*($A6*Model!$B$37/(1+Inputs!$B$23)-$A6*(Inputs!$B$26+Inputs!$B$27)*Model!$B$37-Model!$B$38)-(Model!$B$13+Model!$B$23+Model!$B$24) -> 4.6527793 | D6: =Model!$C$6*($A6*Model!$B$37/(1+Inputs!$B$23)-$A6*(Inputs!$B$26+Inputs!$B$27)*Model!$B$37-Model!$B$38)-(Model!$C$13+Model!$C$23+Model!$C$24) -> 673.2639 | E6: =Model!$D$6*($A6*Model!$B$37/(1+Inputs!$B$23)-$A6*(Inputs!$B$26+Inputs!$B$27)*Model!$B$37-Model!$B$38)-(Model!$D$13+Model!$D$23+Model!$D$24) -> 1456.5278 | F6: =Model!$B$6*($A6*Model!$B$37/(1+Inputs!$B$23)-$A6*(Inputs!$B$26+Inputs!$B$27)*Model!$B$37-Model!$B$38)-(Model!$B$29-Model!$B$21) -> -578.68055 | G6: =Model!$C$6*($A6*Model!$B$37/(1+Inputs!$B$23)-$A6*(Inputs!$B$26+Inputs!$B$27)*Model!$B$37-Model!$B$38)-(Model!$C$29-Model!$C$21) -> -743.40277 | H6: =Model!$D$6*($A6*Model!$B$37/(1+Inputs!$B$23)-$A6*(Inputs!$B$26+Inputs!$B$27)*Model!$B$37-Model!$B$38)-(Model!$D$29-Model!$D$21) -> -876.80554
A7: 3.99 | B7: =A7*Inputs!$B$21/Inputs!$B$20 -> 39.971964 | C7: =Model!$B$6*($A7*Model!$B$37/(1+Inputs!$B$23)-$A7*(Inputs!$B$26+Inputs!$B$27)*Model!$B$37-Model!$B$38)-(Model!$B$13+Model!$B$23+Model!$B$24) -> 90.26129 | D7: =Model!$C$6*($A7*Model!$B$37/(1+Inputs!$B$23)-$A7*(Inputs!$B$26+Inputs!$B$27)*Model!$B$37-Model!$B$38)-(Model!$C$13+Model!$C$23+Model!$C$24) -> 1101.3064 | E7: =Model!$D$6*($A7*Model!$B$37/(1+Inputs!$B$23)-$A7*(Inputs!$B$26+Inputs!$B$27)*Model!$B$37-Model!$B$38)-(Model!$D$13+Model!$D$23+Model!$D$24) -> 2312.6129 | F7: =Model!$B$6*($A7*Model!$B$37/(1+Inputs!$B$23)-$A7*(Inputs!$B$26+Inputs!$B$27)*Model!$B$37-Model!$B$38)-(Model!$B$29-Model!$B$21) -> -493.07204 | G7: =Model!$C$6*($A7*Model!$B$37/(1+Inputs!$B$23)-$A7*(Inputs!$B$26+Inputs!$B$27)*Model!$B$37-Model!$B$38)-(Model!$C$29-Model!$C$21) -> -315.36022 | H7: =Model!$D$6*($A7*Model!$B$37/(1+Inputs!$B$23)-$A7*(Inputs!$B$26+Inputs!$B$27)*Model!$B$37-Model!$B$38)-(Model!$D$29-Model!$D$21) -> -20.720437
A8: 4.99 | B8: =A8*Inputs!$B$21/Inputs!$B$20 -> 49.99 | C8: =Model!$B$6*($A8*Model!$B$37/(1+Inputs!$B$23)-$A8*(Inputs!$B$26+Inputs!$B$27)*Model!$B$37-Model!$B$38)-(Model!$B$13+Model!$B$23+Model!$B$24) -> 175.8698 | D8: =Model!$C$6*($A8*Model!$B$37/(1+Inputs!$B$23)-$A8*(Inputs!$B$26+Inputs!$B$27)*Model!$B$37-Model!$B$38)-(Model!$C$13+Model!$C$23+Model!$C$24) -> 1529.349 | E8: =Model!$D$6*($A8*Model!$B$37/(1+Inputs!$B$23)-$A8*(Inputs!$B$26+Inputs!$B$27)*Model!$B$37-Model!$B$38)-(Model!$D$13+Model!$D$23+Model!$D$24) -> 3168.698 | F8: =Model!$B$6*($A8*Model!$B$37/(1+Inputs!$B$23)-$A8*(Inputs!$B$26+Inputs!$B$27)*Model!$B$37-Model!$B$38)-(Model!$B$29-Model!$B$21) -> -407.46353 | G8: =Model!$C$6*($A8*Model!$B$37/(1+Inputs!$B$23)-$A8*(Inputs!$B$26+Inputs!$B$27)*Model!$B$37-Model!$B$38)-(Model!$C$29-Model!$C$21) -> 112.68233 | H8: =Model!$D$6*($A8*Model!$B$37/(1+Inputs!$B$23)-$A8*(Inputs!$B$26+Inputs!$B$27)*Model!$B$37-Model!$B$38)-(Model!$D$29-Model!$D$21) -> 835.36467
A9: 5.99 | B9: =A9*Inputs!$B$21/Inputs!$B$20 -> 60.008036 | C9: =Model!$B$6*($A9*Model!$B$37/(1+Inputs!$B$23)-$A9*(Inputs!$B$26+Inputs!$B$27)*Model!$B$37-Model!$B$38)-(Model!$B$13+Model!$B$23+Model!$B$24) -> 261.47831 | D9: =Model!$C$6*($A9*Model!$B$37/(1+Inputs!$B$23)-$A9*(Inputs!$B$26+Inputs!$B$27)*Model!$B$37-Model!$B$38)-(Model!$C$13+Model!$C$23+Model!$C$24) -> 1957.3916 | E9: =Model!$D$6*($A9*Model!$B$37/(1+Inputs!$B$23)-$A9*(Inputs!$B$26+Inputs!$B$27)*Model!$B$37-Model!$B$38)-(Model!$D$13+Model!$D$23+Model!$D$24) -> 4024.7831 | F9: =Model!$B$6*($A9*Model!$B$37/(1+Inputs!$B$23)-$A9*(Inputs!$B$26+Inputs!$B$27)*Model!$B$37-Model!$B$38)-(Model!$B$29-Model!$B$21) -> -321.85502 | G9: =Model!$C$6*($A9*Model!$B$37/(1+Inputs!$B$23)-$A9*(Inputs!$B$26+Inputs!$B$27)*Model!$B$37-Model!$B$38)-(Model!$C$29-Model!$C$21) -> 540.72489 | H9: =Model!$D$6*($A9*Model!$B$37/(1+Inputs!$B$23)-$A9*(Inputs!$B$26+Inputs!$B$27)*Model!$B$37-Model!$B$38)-(Model!$D$29-Model!$D$21) -> 1691.4498
A10: 6.99 | B10: =A10*Inputs!$B$21/Inputs!$B$20 -> 70.026072 | C10: =Model!$B$6*($A10*Model!$B$37/(1+Inputs!$B$23)-$A10*(Inputs!$B$26+Inputs!$B$27)*Model!$B$37-Model!$B$38)-(Model!$B$13+Model!$B$23+Model!$B$24) -> 347.08682 | D10: =Model!$C$6*($A10*Model!$B$37/(1+Inputs!$B$23)-$A10*(Inputs!$B$26+Inputs!$B$27)*Model!$B$37-Model!$B$38)-(Model!$C$13+Model!$C$23+Model!$C$24) -> 2385.4341 | E10: =Model!$D$6*($A10*Model!$B$37/(1+Inputs!$B$23)-$A10*(Inputs!$B$26+Inputs!$B$27)*Model!$B$37-Model!$B$38)-(Model!$D$13+Model!$D$23+Model!$D$24) -> 4880.8682 | F10: =Model!$B$6*($A10*Model!$B$37/(1+Inputs!$B$23)-$A10*(Inputs!$B$26+Inputs!$B$27)*Model!$B$37-Model!$B$38)-(Model!$B$29-Model!$B$21) -> -236.24651 | G10: =Model!$C$6*($A10*Model!$B$37/(1+Inputs!$B$23)-$A10*(Inputs!$B$26+Inputs!$B$27)*Model!$B$37-Model!$B$38)-(Model!$C$29-Model!$C$21) -> 968.76744 | H10: =Model!$D$6*($A10*Model!$B$37/(1+Inputs!$B$23)-$A10*(Inputs!$B$26+Inputs!$B$27)*Model!$B$37-Model!$B$38)-(Model!$D$29-Model!$D$21) -> 2547.5349
A11: 7.99 | B11: =A11*Inputs!$B$21/Inputs!$B$20 -> 80.044108 | C11: =Model!$B$6*($A11*Model!$B$37/(1+Inputs!$B$23)-$A11*(Inputs!$B$26+Inputs!$B$27)*Model!$B$37-Model!$B$38)-(Model!$B$13+Model!$B$23+Model!$B$24) -> 432.69533 | D11: =Model!$C$6*($A11*Model!$B$37/(1+Inputs!$B$23)-$A11*(Inputs!$B$26+Inputs!$B$27)*Model!$B$37-Model!$B$38)-(Model!$C$13+Model!$C$23+Model!$C$24) -> 2813.4767 | E11: =Model!$D$6*($A11*Model!$B$37/(1+Inputs!$B$23)-$A11*(Inputs!$B$26+Inputs!$B$27)*Model!$B$37-Model!$B$38)-(Model!$D$13+Model!$D$23+Model!$D$24) -> 5736.9533 | F11: =Model!$B$6*($A11*Model!$B$37/(1+Inputs!$B$23)-$A11*(Inputs!$B$26+Inputs!$B$27)*Model!$B$37-Model!$B$38)-(Model!$B$29-Model!$B$21) -> -150.638 | G11: =Model!$C$6*($A11*Model!$B$37/(1+Inputs!$B$23)-$A11*(Inputs!$B$26+Inputs!$B$27)*Model!$B$37-Model!$B$38)-(Model!$C$29-Model!$C$21) -> 1396.81 | H11: =Model!$D$6*($A11*Model!$B$37/(1+Inputs!$B$23)-$A11*(Inputs!$B$26+Inputs!$B$27)*Model!$B$37-Model!$B$38)-(Model!$D$29-Model!$D$21) -> 3403.62
A12: 9.99 | B12: =A12*Inputs!$B$21/Inputs!$B$20 -> 100.08018 | C12: =Model!$B$6*($A12*Model!$B$37/(1+Inputs!$B$23)-$A12*(Inputs!$B$26+Inputs!$B$27)*Model!$B$37-Model!$B$38)-(Model!$B$13+Model!$B$23+Model!$B$24) -> 603.91235 | D12: =Model!$C$6*($A12*Model!$B$37/(1+Inputs!$B$23)-$A12*(Inputs!$B$26+Inputs!$B$27)*Model!$B$37-Model!$B$38)-(Model!$C$13+Model!$C$23+Model!$C$24) -> 3669.5618 | E12: =Model!$D$6*($A12*Model!$B$37/(1+Inputs!$B$23)-$A12*(Inputs!$B$26+Inputs!$B$27)*Model!$B$37-Model!$B$38)-(Model!$D$13+Model!$D$23+Model!$D$24) -> 7449.1235 | F12: =Model!$B$6*($A12*Model!$B$37/(1+Inputs!$B$23)-$A12*(Inputs!$B$26+Inputs!$B$27)*Model!$B$37-Model!$B$38)-(Model!$B$29-Model!$B$21) -> 20.579018 | G12: =Model!$C$6*($A12*Model!$B$37/(1+Inputs!$B$23)-$A12*(Inputs!$B$26+Inputs!$B$27)*Model!$B$37-Model!$B$38)-(Model!$C$29-Model!$C$21) -> 2252.8951 | H12: =Model!$D$6*($A12*Model!$B$37/(1+Inputs!$B$23)-$A12*(Inputs!$B$26+Inputs!$B$27)*Model!$B$37-Model!$B$38)-(Model!$D$29-Model!$D$21) -> 5115.7902
A14: Check: the row matching your current monthly price should equal the Model sheet's profit lines.
